nameko_memcached.py
nameko_memcached-0.1.0.dist-info/METADATA
nameko_memcached-0.1.0.dist-info/RECORD
nameko_memcached-0.1.0.dist-info/WHEEL
nameko_memcached-0.1.0.dist-info/top_level.txt
