Metadata-Version: 2.1
Name: nameko-memcached
Version: 0.1.0
Summary: Memcached dependency for nameko services
Home-page: https://github.com/frisellcpl/nameko-memcached/
Author: frisellcpl
Author-email: johan@trell.se
License: Apache License, Version 2.0
Platform: UNKNOWN
Classifier: Development Status :: 3 - Alpha
Classifier: License :: OSI Approved :: Apache Software License
Classifier: Programming Language :: Python :: 2
Classifier: Programming Language :: Python :: 2.7
Classifier: Programming Language :: Python :: 3
Classifier: Programming Language :: Python :: 3.3
Classifier: Programming Language :: Python :: 3.4
Classifier: Programming Language :: Python :: 3.5
Classifier: Programming Language :: Python :: 3.6
Requires-Dist: nameko (>=2.0.0)
Requires-Dist: python-binary-memcached
